cubestat/__init__.py
cubestat/colors.py
cubestat/common.py
cubestat/cubestat.py
cubestat/data.py
cubestat/input.py
cubestat/metrics_registry.py
cubestat/screen.py
cubestat/metrics/__init__.py
cubestat/metrics/accel.py
cubestat/metrics/base_metric.py
cubestat/metrics/cpu.py
cubestat/metrics/disk.py
cubestat/metrics/gpu.py
cubestat/metrics/memory.py
cubestat/metrics/mock.py
cubestat/metrics/network.py
cubestat/metrics/power.py
cubestat/metrics/swap.py
cubestat/platforms/__init__.py
cubestat/platforms/factory.py
cubestat/platforms/linux.py
cubestat/platforms/macos.py
cubestat-0.3.4.dist-info/LICENSE
cubestat-0.3.4.dist-info/METADATA
cubestat-0.3.4.dist-info/WHEEL
cubestat-0.3.4.dist-info/entry_points.txt
cubestat-0.3.4.dist-info/top_level.txt
cubestat-0.3.4.dist-info/RECORD
